{"title":"workshop-quarto","markdown":{"yaml":{"title":"workshop-quarto"},"headingText":"Nikola Tesla","containsRefs":false,"markdown":"\n\n\n## Informações Básicas e Origem\n\nNikola Tesla (em sérvio: Никола Тесла; pronunciação sérvia: [nǐkola têsla]; Smiljan, Império Austríaco, 10 de julho de 1856 — Nova Iorque, 7 de janeiro de 1943) foi um inventor, engenheiro eletrotécnico e engenheiro mecânico sérvio, mais conhecido por suas contribuições ao projeto do moderno sistema de fornecimento de eletricidade em corrente alternada (CA).\nNascido e criado no Império Austríaco, Tesla estudou engenharia e física na década de 1870 sem se formar, e ganhou experiência prática no início da década de 1880 trabalhando em telefonia e na Continental Edison, na nova indústria de energia elétrica.\n\n## Emigração e Carreira nos EUA\n\nEm 1884, emigrou para os Estados Unidos e se naturalizou cidadão americano.\nEle trabalhou por um curto período na Edison Machine Works, em Nova Iorque, antes de começar por conta própria.\nCom a ajuda de parceiros para financiar e comercializar suas ideias, Tesla montou laboratórios e empresas em Nova Iorque para desenvolver uma variedade de dispositivos elétricos e mecânicos.\nSeu motor de indução de corrente alternada e patentes relacionadas ao sistema polifásico, licenciadas pela Westinghouse Electric em 1888, lhe renderam uma quantia considerável de dinheiro e se tornaram a pedra angular do sistema polifásico que a empresa acabou comercializando.\n\n## Experimentos e Inovações\n\nTentando desenvolver invenções que pudesse patentear e comercializar, Tesla conduziu uma série de experimentos com osciladores/geradores mecânicos, tubos de descarga elétrica e radiografia.\nEle também construiu um barco de controle remoto, um dos primeiros já exibidos.\nTesla tornou-se conhecido como inventor e demonstrou suas realizações para celebridades e patronos ricos em seu laboratório, e destacou-se por seu talento em palestras públicas.\n\n## Energia Sem Fio e Experimentos Avançados\n\nDurante a década de 1890, Tesla seguiu suas ideias para iluminação sem fio e distribuição mundial de energia elétrica sem fio em seus experimentos de alta tensão e alta frequência em Nova Iorque e Colorado Springs.\nEm 1893, ele fez pronunciamentos sobre a possibilidade de comunicação sem fio com seus dispositivos.\nTesla tentou colocar essas ideias em uso prático em seu projeto inacabado da Wardenclyffe Tower, uma transmissora sem fio intercontinental de comunicações e energia, mas ficou sem dinheiro antes que pudesse concluí-lo.\n\n## Últimos Anos e Legado\n\nDepois de Wardenclyffe, Tesla experimentou uma série de invenções nas décadas de 1910 e 1920 com graus variados de sucesso.\nTendo gasto a maior parte de seu dinheiro, Tesla morava em uma série de hotéis de Nova Iorque, deixando para trás contas não pagas.\nEle morreu na cidade de Nova Iorque em janeiro de 1943.\nO trabalho de Tesla caiu em relativa obscuridade após sua morte, até 1960, quando a Conferência Geral de Pesos e Medidas nomeou a unidade SI de densidade de fluxo magnético como tesla em sua homenagem.\nHouve um ressurgimento do interesse popular em Tesla desde os anos 1990.\n","srcMarkdownNoYaml":"\n\n# Nikola Tesla\n\n## Informações Básicas e Origem\n\nNikola Tesla (em sérvio: Никола Тесла; pronunciação sérvia: [nǐkola têsla]; Smiljan, Império Austríaco, 10 de julho de 1856 — Nova Iorque, 7 de janeiro de 1943) foi um inventor, engenheiro eletrotécnico e engenheiro mecânico sérvio, mais conhecido por suas contribuições ao projeto do moderno sistema de fornecimento de eletricidade em corrente alternada (CA).\nNascido e criado no Império Austríaco, Tesla estudou engenharia e física na década de 1870 sem se formar, e ganhou experiência prática no início da década de 1880 trabalhando em telefonia e na Continental Edison, na nova indústria de energia elétrica.\n\n## Emigração e Carreira nos EUA\n\nEm 1884, emigrou para os Estados Unidos e se naturalizou cidadão americano.\nEle trabalhou por um curto período na Edison Machine Works, em Nova Iorque, antes de começar por conta própria.\nCom a ajuda de parceiros para financiar e comercializar suas ideias, Tesla montou laboratórios e empresas em Nova Iorque para desenvolver uma variedade de dispositivos elétricos e mecânicos.\nSeu motor de indução de corrente alternada e patentes relacionadas ao sistema polifásico, licenciadas pela Westinghouse Electric em 1888, lhe renderam uma quantia considerável de dinheiro e se tornaram a pedra angular do sistema polifásico que a empresa acabou comercializando.\n\n## Experimentos e Inovações\n\nTentando desenvolver invenções que pudesse patentear e comercializar, Tesla conduziu uma série de experimentos com osciladores/geradores mecânicos, tubos de descarga elétrica e radiografia.\nEle também construiu um barco de controle remoto, um dos primeiros já exibidos.\nTesla tornou-se conhecido como inventor e demonstrou suas realizações para celebridades e patronos ricos em seu laboratório, e destacou-se por seu talento em palestras públicas.\n\n## Energia Sem Fio e Experimentos Avançados\n\nDurante a década de 1890, Tesla seguiu suas ideias para iluminação sem fio e distribuição mundial de energia elétrica sem fio em seus experimentos de alta tensão e alta frequência em Nova Iorque e Colorado Springs.\nEm 1893, ele fez pronunciamentos sobre a possibilidade de comunicação sem fio com seus dispositivos.\nTesla tentou colocar essas ideias em uso prático em seu projeto inacabado da Wardenclyffe Tower, uma transmissora sem fio intercontinental de comunicações e energia, mas ficou sem dinheiro antes que pudesse concluí-lo.\n\n## Últimos Anos e Legado\n\nDepois de Wardenclyffe, Tesla experimentou uma série de invenções nas décadas de 1910 e 1920 com graus variados de sucesso.\nTendo gasto a maior parte de seu dinheiro, Tesla morava em uma série de hotéis de Nova Iorque, deixando para trás contas não pagas.\nEle morreu na cidade de Nova Iorque em janeiro de 1943.\nO trabalho de Tesla caiu em relativa obscuridade após sua morte, até 1960, quando a Conferência Geral de Pesos e Medidas nomeou a unidade SI de densidade de fluxo magnético como tesla em sua homenagem.\nHouve um ressurgimento do interesse popular em Tesla desde os anos 1990.\n"},"formats":{"html":{"identifier":{"display-name":"HTML","target-format":"html","base-format":"html"},"execute":{"fig-width":7,"fig-height":5,"fig-format":"retina","fig-dpi":96,"df-print":"default","error":false,"eval":true,"cache":null,"freeze":false,"echo":true,"output":true,"warning":true,"include":true,"keep-md":false,"keep-ipynb":false,"ipynb":null,"enabled":null,"daemon":null,"daemon-restart":false,"debug":false,"ipynb-filters":[],"ipynb-shell-interactivity":null,"plotly-connected":true,"engine":"markdown"},"render":{"keep-tex":false,"keep-typ":false,"keep-source":false,"keep-hidden":false,"prefer-html":false,"output-divs":true,"output-ext":"html","fig-align":"default","fig-pos":null,"fig-env":null,"code-fold":"none","code-overflow":"scroll","code-link":false,"code-line-numbers":false,"code-tools":false,"tbl-colwidths":"auto","merge-includes":true,"inline-includes":false,"preserve-yaml":false,"latex-auto-mk":true,"latex-auto-install":true,"latex-clean":true,"latex-min-runs":1,"latex-max-runs":10,"latex-makeindex":"makeindex","latex-makeindex-opts":[],"latex-tlmgr-opts":[],"latex-input-paths":[],"latex-output-dir":null,"link-external-icon":false,"link-external-newwindow":false,"self-contained-math":false,"format-resources":[],"notebook-links":true},"pandoc":{"standalone":true,"wrap":"none","default-image-extension":"png","to":"html","css":["styles.css"],"toc":true,"output-file":"index.html"},"language":{"toc-title-document":"Table of contents","toc-title-website":"On this page","related-formats-title":"Other Formats","related-notebooks-title":"Notebooks","source-notebooks-prefix":"Source","other-links-title":"Other Links","code-links-title":"Code Links","launch-dev-container-title":"Launch Dev Container","launch-binder-title":"Launch Binder","article-notebook-label":"Article Notebook","notebook-preview-download":"Download Notebook","notebook-preview-download-src":"Download Source","notebook-preview-back":"Back to Article","manuscript-meca-bundle":"MECA Bundle","section-title-abstract":"Abstract","section-title-appendices":"Appendices","section-title-footnotes":"Footnotes","section-title-references":"References","section-title-reuse":"Reuse","section-title-copyright":"Copyright","section-title-citation":"Citation","appendix-attribution-cite-as":"For attribution, please cite this work as:","appendix-attribution-bibtex":"BibTeX citation:","appendix-view-license":"View License","title-block-author-single":"Author","title-block-author-plural":"Authors","title-block-affiliation-single":"Affiliation","title-block-affiliation-plural":"Affiliations","title-block-published":"Published","title-block-modified":"Modified","title-block-keywords":"Keywords","callout-tip-title":"Tip","callout-note-title":"Note","callout-warning-title":"Warning","callout-important-title":"Important","callout-caution-title":"Caution","code-summary":"Code","code-tools-menu-caption":"Code","code-tools-show-all-code":"Show All Code","code-tools-hide-all-code":"Hide All Code","code-tools-view-source":"View Source","code-tools-source-code":"Source Code","tools-share":"Share","tools-download":"Download","code-line":"Line","code-lines":"Lines","copy-button-tooltip":"Copy to Clipboard","copy-button-tooltip-success":"Copied!","repo-action-links-edit":"Edit this page","repo-action-links-source":"View source","repo-action-links-issue":"Report an issue","back-to-top":"Back to top","search-no-results-text":"No results","search-matching-documents-text":"matching documents","search-copy-link-title":"Copy link to search","search-hide-matches-text":"Hide additional matches","search-more-match-text":"more match in this document","search-more-matches-text":"more matches in this document","search-clear-button-title":"Clear","search-text-placeholder":"","search-detached-cancel-button-title":"Cancel","search-submit-button-title":"Submit","search-label":"Search","toggle-section":"Toggle section","toggle-sidebar":"Toggle sidebar navigation","toggle-dark-mode":"Toggle dark mode","toggle-reader-mode":"Toggle reader mode","toggle-navigation":"Toggle navigation","crossref-fig-title":"Figure","crossref-tbl-title":"Table","crossref-lst-title":"Listing","crossref-thm-title":"Theorem","crossref-lem-title":"Lemma","crossref-cor-title":"Corollary","crossref-prp-title":"Proposition","crossref-cnj-title":"Conjecture","crossref-def-title":"Definition","crossref-exm-title":"Example","crossref-exr-title":"Exercise","crossref-ch-prefix":"Chapter","crossref-apx-prefix":"Appendix","crossref-sec-prefix":"Section","crossref-eq-prefix":"Equation","crossref-lof-title":"List of Figures","crossref-lot-title":"List of Tables","crossref-lol-title":"List of Listings","environment-proof-title":"Proof","environment-remark-title":"Remark","environment-solution-title":"Solution","listing-page-order-by":"Order By","listing-page-order-by-default":"Default","listing-page-order-by-date-asc":"Oldest","listing-page-order-by-date-desc":"Newest","listing-page-order-by-number-desc":"High to Low","listing-page-order-by-number-asc":"Low to High","listing-page-field-date":"Date","listing-page-field-title":"Title","listing-page-field-description":"Description","listing-page-field-author":"Author","listing-page-field-filename":"File Name","listing-page-field-filemodified":"Modified","listing-page-field-subtitle":"Subtitle","listing-page-field-readingtime":"Reading Time","listing-page-field-wordcount":"Word Count","listing-page-field-categories":"Categories","listing-page-minutes-compact":"{0} min","listing-page-category-all":"All","listing-page-no-matches":"No matching items","listing-page-words":"{0} words","listing-page-filter":"Filter","draft":"Draft"},"metadata":{"lang":"en","fig-responsive":true,"quarto-version":"1.6.32","editor":"visual","theme":"cosmo","title":"workshop-quarto"},"extensions":{"book":{"multiFile":true}}}},"projectFormats":["html"]}